lythonic/__init__.py
lythonic/config.py
lythonic/misc.py
lythonic/periodic.py
lythonic/py.typed
lythonic/types.py
lythonic/compose/__init__.py
lythonic/compose/cli.py
lythonic/compose/logic.py
lythonic/examples/__init__.py
lythonic/examples/cashflow_tracking/__init__.py
lythonic/examples/cashflow_tracking/api.py
lythonic/state/__init__.py
lythonic/state/user.py
lythonic-0.0.8.dist-info/METADATA
lythonic-0.0.8.dist-info/WHEEL
lythonic-0.0.8.dist-info/entry_points.txt
lythonic-0.0.8.dist-info/licenses/LICENSE
lythonic-0.0.8.dist-info/RECORD
