Metadata-Version: 2.4
Name: lythonic
Version: 0.0.8
Summary: Light-weight pythonic db integration - powered by the best of all time: sqlite and pydantic
Project-URL: Repository, https://github.com/walnutgeek/lythonic
Author-email: Walnut Geek <wg@walnutgeek.com>
License-Expression: MIT
License-File: LICENSE
Classifier: Development Status :: 4 - Beta
Classifier: Intended Audience :: Developers
Classifier: Operating System :: OS Independent
Classifier: Programming Language :: Python
Classifier: Programming Language :: Python :: 3
Classifier: Programming Language :: Python :: 3.11
Classifier: Programming Language :: Python :: 3.12
Classifier: Programming Language :: Python :: 3.13
Classifier: Typing :: Typed
Requires-Python: <4.0,>=3.11
Requires-Dist: pydantic
